[
  {
    "problem_id": "depth03_prob0000",
    "depth": 3,
    "question": "Diana earns $8 per hour and works 6 hours. Diana gives away $3 on boxes. Diana also receives a $9 bonus. How much $ does Diana have in the end?",
    "ground_truth": 54.0,
    "intermediate_values": [
      48.0,
      45.0,
      54.0
    ],
    "operations": [
      "multiply",
      "derived",
      "derived"
    ],
    "answer_unit": "$"
  },
  {
    "problem_id": "depth03_prob0001",
    "depth": 3,
    "question": "Eve receives $20 per hour and works 7 hours. Eve doubles Eve's current $ total. A 25% fee is deducted from Eve's total. How much $ does Eve have in the end?",
    "ground_truth": 210.0,
    "intermediate_values": [
      140.0,
      280.0,
      210.0
    ],
    "operations": [
      "multiply",
      "derived",
      "derived"
    ],
    "answer_unit": "$"
  },
  {
    "problem_id": "depth03_prob0002",
    "depth": 3,
    "question": "Alice gathers $12 per hour and works 9 hours. Alice uses $5 on apples. Alice doubles Alice's current $ total. How much $ does Alice have in the end?",
    "ground_truth": 206.0,
    "intermediate_values": [
      108.0,
      103.0,
      206.0
    ],
    "operations": [
      "multiply",
      "derived",
      "derived"
    ],
    "answer_unit": "$"
  },
  {
    "problem_id": "depth03_prob0003",
    "depth": 3,
    "question": "Carlos earns $19 per hour and works 7 hours. Carlos spends a third of Carlos's remaining $ on boxes. Carlos then orders 4 books at $5 each. How much $ does Carlos have in the end?",
    "ground_truth": 68.66666666666667,
    "intermediate_values": [
      133.0,
      88.66666666666667,
      68.66666666666667
    ],
    "operations": [
      "multiply",
      "derived",
      "derived"
    ],
    "answer_unit": "$"
  },
  {
    "problem_id": "depth03_prob0004",
    "depth": 3,
    "question": "Frank receives $11 per hour and works 6 hours. Frank doubles Frank's current $ total. Frank then buys 4 apples at $7 each. How much $ does Frank have in the end?",
    "ground_truth": 104.0,
    "intermediate_values": [
      66.0,
      132.0,
      104.0
    ],
    "operations": [
      "multiply",
      "derived",
      "derived"
    ],
    "answer_unit": "$"
  },
  {
    "problem_id": "depth03_prob0005",
    "depth": 3,
    "question": "Henry collects $20 per hour and works 6 hours. Henry spends a third of Henry's remaining $ on apples. Henry doubles Henry's current $ total. How much $ does Henry have in the end?",
    "ground_truth": 160.0,
    "intermediate_values": [
      120.0,
      80.0,
      160.0
    ],
    "operations": [
      "multiply",
      "derived",
      "derived"
    ],
    "answer_unit": "$"
  },
  {
    "problem_id": "depth03_prob0006",
    "depth": 3,
    "question": "Alice gathers $9 per hour and works 4 hours. Alice then picks up 3 apples at $5 each. Alice spends $3 on books. How much $ does Alice have in the end?",
    "ground_truth": 18.0,
    "intermediate_values": [
      36.0,
      21.0,
      18.0
    ],
    "operations": [
      "multiply",
      "derived",
      "derived"
    ],
    "answer_unit": "$"
  },
  {
    "problem_id": "depth03_prob0007",
    "depth": 3,
    "question": "Alice gathers $19 per hour and works 8 hours. Alice doubles Alice's current $ total. Alice uses $9 on apples. How much $ does Alice have in the end?",
    "ground_truth": 295.0,
    "intermediate_values": [
      152.0,
      304.0,
      295.0
    ],
    "operations": [
      "multiply",
      "derived",
      "derived"
    ],
    "answer_unit": "$"
  },
  {
    "problem_id": "depth03_prob0008",
    "depth": 3,
    "question": "Alice earns $15 per hour and works 9 hours. Alice spends a third of Alice's remaining $ on books. Alice then buys 2 apples at $2 each. How much $ does Alice have in the end?",
    "ground_truth": 86.0,
    "intermediate_values": [
      135.0,
      90.0,
      86.0
    ],
    "operations": [
      "multiply",
      "derived",
      "derived"
    ],
    "answer_unit": "$"
  },
  {
    "problem_id": "depth03_prob0009",
    "depth": 3,
    "question": "Alice gathers $15 per hour and works 10 hours. Alice doubles Alice's current $ total. Alice then picks up 3 boxes at $8 each. How much $ does Alice have in the end?",
    "ground_truth": 276.0,
    "intermediate_values": [
      150.0,
      300.0,
      276.0
    ],
    "operations": [
      "multiply",
      "derived",
      "derived"
    ],
    "answer_unit": "$"
  },
  {
    "problem_id": "depth03_prob0010",
    "depth": 3,
    "question": "Henry collects $17 per hour and works 6 hours. Henry also receives a $7 bonus. Henry spends half of Henry's remaining $ on apples. How much $ does Henry have in the end?",
    "ground_truth": 54.5,
    "intermediate_values": [
      102.0,
      109.0,
      54.5
    ],
    "operations": [
      "multiply",
      "derived",
      "derived"
    ],
    "answer_unit": "$"
  },
  {
    "problem_id": "depth03_prob0011",
    "depth": 3,
    "question": "Eve earns $11 per hour and works 7 hours. Eve spends $8 on apples. A 20% fee is deducted from Eve's total. How much $ does Eve have in the end?",
    "ground_truth": 55.2,
    "intermediate_values": [
      77.0,
      69.0,
      55.2
    ],
    "operations": [
      "multiply",
      "derived",
      "derived"
    ],
    "answer_unit": "$"
  },
  {
    "problem_id": "depth03_prob0012",
    "depth": 3,
    "question": "Diana collects $19 per hour and works 10 hours. Diana gives away $3 on books. Diana doubles Diana's current $ total. How much $ does Diana have in the end?",
    "ground_truth": 374.0,
    "intermediate_values": [
      190.0,
      187.0,
      374.0
    ],
    "operations": [
      "multiply",
      "derived",
      "derived"
    ],
    "answer_unit": "$"
  },
  {
    "problem_id": "depth03_prob0013",
    "depth": 3,
    "question": "Grace collects $20 per hour and works 3 hours. Grace spends $5 on boxes. Grace doubles Grace's current $ total. How much $ does Grace have in the end?",
    "ground_truth": 110.0,
    "intermediate_values": [
      60.0,
      55.0,
      110.0
    ],
    "operations": [
      "multiply",
      "derived",
      "derived"
    ],
    "answer_unit": "$"
  },
  {
    "problem_id": "depth03_prob0014",
    "depth": 3,
    "question": "Henry receives $17 per hour and works 4 hours. Henry spends half of Henry's remaining $ on apples. Henry doubles Henry's current $ total. How much $ does Henry have in the end?",
    "ground_truth": 68.0,
    "intermediate_values": [
      68.0,
      34.0,
      68.0
    ],
    "operations": [
      "multiply",
      "derived",
      "derived"
    ],
    "answer_unit": "$"
  },
  {
    "problem_id": "depth03_prob0015",
    "depth": 3,
    "question": "Frank receives $12 per hour and works 5 hours. Frank doubles Frank's current $ total. Frank also receives a $9 bonus. How much $ does Frank have in the end?",
    "ground_truth": 129.0,
    "intermediate_values": [
      60.0,
      120.0,
      129.0
    ],
    "operations": [
      "multiply",
      "derived",
      "derived"
    ],
    "answer_unit": "$"
  },
  {
    "problem_id": "depth03_prob0016",
    "depth": 3,
    "question": "Carlos collects $18 per hour and works 8 hours. Carlos also receives a $11 bonus. Carlos doubles Carlos's current $ total. How much $ does Carlos have in the end?",
    "ground_truth": 310.0,
    "intermediate_values": [
      144.0,
      155.0,
      310.0
    ],
    "operations": [
      "multiply",
      "derived",
      "derived"
    ],
    "answer_unit": "$"
  },
  {
    "problem_id": "depth03_prob0017",
    "depth": 3,
    "question": "Alice receives $9 per hour and works 3 hours. Alice donates $6 on books. Alice spends a quarter of Alice's remaining $ on boxes. How much $ does Alice have in the end?",
    "ground_truth": 15.75,
    "intermediate_values": [
      27.0,
      21.0,
      15.75
    ],
    "operations": [
      "multiply",
      "derived",
      "derived"
    ],
    "answer_unit": "$"
  },
  {
    "problem_id": "depth03_prob0018",
    "depth": 3,
    "question": "Henry earns $20 per hour and works 3 hours. Henry gives away $8 on books. Henry doubles Henry's current $ total. How much $ does Henry have in the end?",
    "ground_truth": 104.0,
    "intermediate_values": [
      60.0,
      52.0,
      104.0
    ],
    "operations": [
      "multiply",
      "derived",
      "derived"
    ],
    "answer_unit": "$"
  },
  {
    "problem_id": "depth03_prob0019",
    "depth": 3,
    "question": "Alice receives $9 per hour and works 4 hours. Alice donates $2 on boxes. Alice spends a third of Alice's remaining $ on books. How much $ does Alice have in the end?",
    "ground_truth": 22.666666666666668,
    "intermediate_values": [
      36.0,
      34.0,
      22.666666666666668
    ],
    "operations": [
      "multiply",
      "derived",
      "derived"
    ],
    "answer_unit": "$"
  },
  {
    "problem_id": "depth03_prob0020",
    "depth": 3,
    "question": "Henry earns $11 per hour and works 8 hours. Henry spends a quarter of Henry's remaining $ on boxes. Henry then purchases 5 books at $4 each. How much $ does Henry have in the end?",
    "ground_truth": 46.0,
    "intermediate_values": [
      88.0,
      66.0,
      46.0
    ],
    "operations": [
      "multiply",
      "derived",
      "derived"
    ],
    "answer_unit": "$"
  },
  {
    "problem_id": "depth03_prob0021",
    "depth": 3,
    "question": "Bob collects $6 per hour and works 7 hours. A 10% fee is deducted from Bob's total. Bob spends half of Bob's remaining $ on apples. How much $ does Bob have in the end?",
    "ground_truth": 18.9,
    "intermediate_values": [
      42.0,
      37.8,
      18.9
    ],
    "operations": [
      "multiply",
      "derived",
      "derived"
    ],
    "answer_unit": "$"
  },
  {
    "problem_id": "depth03_prob0022",
    "depth": 3,
    "question": "Frank earns $8 per hour and works 10 hours. Frank spends $7 on boxes. Frank spends a quarter of Frank's remaining $ on apples. How much $ does Frank have in the end?",
    "ground_truth": 54.75,
    "intermediate_values": [
      80.0,
      73.0,
      54.75
    ],
    "operations": [
      "multiply",
      "derived",
      "derived"
    ],
    "answer_unit": "$"
  },
  {
    "problem_id": "depth03_prob0023",
    "depth": 3,
    "question": "Grace receives $14 per hour and works 8 hours. Grace spends a quarter of Grace's remaining $ on apples. A 10% fee is deducted from Grace's total. How much $ does Grace have in the end?",
    "ground_truth": 75.6,
    "intermediate_values": [
      112.0,
      84.0,
      75.6
    ],
    "operations": [
      "multiply",
      "derived",
      "derived"
    ],
    "answer_unit": "$"
  },
  {
    "problem_id": "depth03_prob0024",
    "depth": 3,
    "question": "Diana collects $10 per hour and works 10 hours. Diana spends a third of Diana's remaining $ on books. Diana then buys 3 apples at $6 each. How much $ does Diana have in the end?",
    "ground_truth": 48.666666666666664,
    "intermediate_values": [
      100.0,
      66.66666666666667,
      48.666666666666664
    ],
    "operations": [
      "multiply",
      "derived",
      "derived"
    ],
    "answer_unit": "$"
  },
  {
    "problem_id": "depth03_prob0025",
    "depth": 3,
    "question": "Henry receives $17 per hour and works 9 hours. Henry also receives a $8 bonus. Henry spends half of Henry's remaining $ on apples. How much $ does Henry have in the end?",
    "ground_truth": 80.5,
    "intermediate_values": [
      153.0,
      161.0,
      80.5
    ],
    "operations": [
      "multiply",
      "derived",
      "derived"
    ],
    "answer_unit": "$"
  },
  {
    "problem_id": "depth03_prob0026",
    "depth": 3,
    "question": "Alice receives $18 per hour and works 10 hours. Alice spends half of Alice's remaining $ on boxes. Alice spends a quarter of Alice's remaining $ on apples. How much $ does Alice have in the end?",
    "ground_truth": 67.5,
    "intermediate_values": [
      180.0,
      90.0,
      67.5
    ],
    "operations": [
      "multiply",
      "derived",
      "derived"
    ],
    "answer_unit": "$"
  },
  {
    "problem_id": "depth03_prob0027",
    "depth": 3,
    "question": "Henry collects $8 per hour and works 6 hours. Henry also receives a $12 bonus. Henry then orders 4 books at $3 each. How much $ does Henry have in the end?",
    "ground_truth": 48.0,
    "intermediate_values": [
      48.0,
      60.0,
      48.0
    ],
    "operations": [
      "multiply",
      "derived",
      "derived"
    ],
    "answer_unit": "$"
  },
  {
    "problem_id": "depth03_prob0028",
    "depth": 3,
    "question": "Eve collects $7 per hour and works 3 hours. Eve also receives a $15 bonus. A 10% fee is deducted from Eve's total. How much $ does Eve have in the end?",
    "ground_truth": 32.4,
    "intermediate_values": [
      21.0,
      36.0,
      32.4
    ],
    "operations": [
      "multiply",
      "derived",
      "derived"
    ],
    "answer_unit": "$"
  },
  {
    "problem_id": "depth03_prob0029",
    "depth": 3,
    "question": "Alice earns $12 per hour and works 7 hours. Alice doubles Alice's current $ total. Alice spends a third of Alice's remaining $ on apples. How much $ does Alice have in the end?",
    "ground_truth": 112.0,
    "intermediate_values": [
      84.0,
      168.0,
      112.0
    ],
    "operations": [
      "multiply",
      "derived",
      "derived"
    ],
    "answer_unit": "$"
  },
  {
    "problem_id": "depth03_prob0030",
    "depth": 3,
    "question": "Frank receives $13 per hour and works 3 hours. A 25% fee is deducted from Frank's total. Frank then orders 2 books at $5 each. How much $ does Frank have in the end?",
    "ground_truth": 19.25,
    "intermediate_values": [
      39.0,
      29.25,
      19.25
    ],
    "operations": [
      "multiply",
      "derived",
      "derived"
    ],
    "answer_unit": "$"
  },
  {
    "problem_id": "depth03_prob0031",
    "depth": 3,
    "question": "Carlos earns $8 per hour and works 8 hours. Carlos spends half of Carlos's remaining $ on boxes. Carlos donates $4 on books. How much $ does Carlos have in the end?",
    "ground_truth": 28.0,
    "intermediate_values": [
      64.0,
      32.0,
      28.0
    ],
    "operations": [
      "multiply",
      "derived",
      "derived"
    ],
    "answer_unit": "$"
  },
  {
    "problem_id": "depth03_prob0032",
    "depth": 3,
    "question": "Frank earns $9 per hour and works 8 hours. A 10% fee is deducted from Frank's total. Frank spends a third of Frank's remaining $ on boxes. How much $ does Frank have in the end?",
    "ground_truth": 43.2,
    "intermediate_values": [
      72.0,
      64.8,
      43.2
    ],
    "operations": [
      "multiply",
      "derived",
      "derived"
    ],
    "answer_unit": "$"
  },
  {
    "problem_id": "depth03_prob0033",
    "depth": 3,
    "question": "Diana gathers $17 per hour and works 9 hours. Diana doubles Diana's current $ total. Diana spends half of Diana's remaining $ on books. How much $ does Diana have in the end?",
    "ground_truth": 153.0,
    "intermediate_values": [
      153.0,
      306.0,
      153.0
    ],
    "operations": [
      "multiply",
      "derived",
      "derived"
    ],
    "answer_unit": "$"
  },
  {
    "problem_id": "depth03_prob0034",
    "depth": 3,
    "question": "Diana receives $8 per hour and works 5 hours. Diana then buys 4 apples at $7 each. A 25% fee is deducted from Diana's total. How much $ does Diana have in the end?",
    "ground_truth": 9.0,
    "intermediate_values": [
      40.0,
      12.0,
      9.0
    ],
    "operations": [
      "multiply",
      "derived",
      "derived"
    ],
    "answer_unit": "$"
  },
  {
    "problem_id": "depth03_prob0035",
    "depth": 3,
    "question": "Diana receives $14 per hour and works 6 hours. Diana also receives a $10 bonus. Diana spends a quarter of Diana's remaining $ on books. How much $ does Diana have in the end?",
    "ground_truth": 70.5,
    "intermediate_values": [
      84.0,
      94.0,
      70.5
    ],
    "operations": [
      "multiply",
      "derived",
      "derived"
    ],
    "answer_unit": "$"
  },
  {
    "problem_id": "depth03_prob0036",
    "depth": 3,
    "question": "Grace earns $9 per hour and works 6 hours. Grace doubles Grace's current $ total. Grace spends a quarter of Grace's remaining $ on books. How much $ does Grace have in the end?",
    "ground_truth": 81.0,
    "intermediate_values": [
      54.0,
      108.0,
      81.0
    ],
    "operations": [
      "multiply",
      "derived",
      "derived"
    ],
    "answer_unit": "$"
  },
  {
    "problem_id": "depth03_prob0037",
    "depth": 3,
    "question": "Henry earns $10 per hour and works 9 hours. Henry doubles Henry's current $ total. Henry spends a third of Henry's remaining $ on books. How much $ does Henry have in the end?",
    "ground_truth": 120.0,
    "intermediate_values": [
      90.0,
      180.0,
      120.0
    ],
    "operations": [
      "multiply",
      "derived",
      "derived"
    ],
    "answer_unit": "$"
  },
  {
    "problem_id": "depth03_prob0038",
    "depth": 3,
    "question": "Alice gathers $6 per hour and works 7 hours. Alice then purchases 3 boxes at $5 each. Alice spends half of Alice's remaining $ on books. How much $ does Alice have in the end?",
    "ground_truth": 13.5,
    "intermediate_values": [
      42.0,
      27.0,
      13.5
    ],
    "operations": [
      "multiply",
      "derived",
      "derived"
    ],
    "answer_unit": "$"
  },
  {
    "problem_id": "depth03_prob0039",
    "depth": 3,
    "question": "Eve earns $11 per hour and works 3 hours. Eve then purchases 2 apples at $6 each. Eve also receives a $6 bonus. How much $ does Eve have in the end?",
    "ground_truth": 27.0,
    "intermediate_values": [
      33.0,
      21.0,
      27.0
    ],
    "operations": [
      "multiply",
      "derived",
      "derived"
    ],
    "answer_unit": "$"
  },
  {
    "problem_id": "depth03_prob0040",
    "depth": 3,
    "question": "Alice gathers $14 per hour and works 9 hours. Alice doubles Alice's current $ total. Alice spends half of Alice's remaining $ on boxes. How much $ does Alice have in the end?",
    "ground_truth": 126.0,
    "intermediate_values": [
      126.0,
      252.0,
      126.0
    ],
    "operations": [
      "multiply",
      "derived",
      "derived"
    ],
    "answer_unit": "$"
  },
  {
    "problem_id": "depth03_prob0041",
    "depth": 3,
    "question": "Grace gathers $9 per hour and works 6 hours. Grace doubles Grace's current $ total. Grace spends a quarter of Grace's remaining $ on books. How much $ does Grace have in the end?",
    "ground_truth": 81.0,
    "intermediate_values": [
      54.0,
      108.0,
      81.0
    ],
    "operations": [
      "multiply",
      "derived",
      "derived"
    ],
    "answer_unit": "$"
  },
  {
    "problem_id": "depth03_prob0042",
    "depth": 3,
    "question": "Henry gathers $18 per hour and works 4 hours. Henry spends a quarter of Henry's remaining $ on books. Henry uses $5 on apples. How much $ does Henry have in the end?",
    "ground_truth": 49.0,
    "intermediate_values": [
      72.0,
      54.0,
      49.0
    ],
    "operations": [
      "multiply",
      "derived",
      "derived"
    ],
    "answer_unit": "$"
  },
  {
    "problem_id": "depth03_prob0043",
    "depth": 3,
    "question": "Bob earns $7 per hour and works 8 hours. A 20% fee is deducted from Bob's total. Bob also receives a $8 bonus. How much $ does Bob have in the end?",
    "ground_truth": 52.8,
    "intermediate_values": [
      56.0,
      44.8,
      52.8
    ],
    "operations": [
      "multiply",
      "derived",
      "derived"
    ],
    "answer_unit": "$"
  },
  {
    "problem_id": "depth03_prob0044",
    "depth": 3,
    "question": "Carlos receives $18 per hour and works 4 hours. Carlos spends half of Carlos's remaining $ on boxes. Carlos spends a quarter of Carlos's remaining $ on apples. How much $ does Carlos have in the end?",
    "ground_truth": 27.0,
    "intermediate_values": [
      72.0,
      36.0,
      27.0
    ],
    "operations": [
      "multiply",
      "derived",
      "derived"
    ],
    "answer_unit": "$"
  },
  {
    "problem_id": "depth03_prob0045",
    "depth": 3,
    "question": "Frank receives $6 per hour and works 8 hours. Frank donates $4 on boxes. Frank then purchases 4 apples at $7 each. How much $ does Frank have in the end?",
    "ground_truth": 16.0,
    "intermediate_values": [
      48.0,
      44.0,
      16.0
    ],
    "operations": [
      "multiply",
      "derived",
      "derived"
    ],
    "answer_unit": "$"
  },
  {
    "problem_id": "depth03_prob0046",
    "depth": 3,
    "question": "Grace receives $7 per hour and works 5 hours. Grace then purchases 2 apples at $7 each. Grace doubles Grace's current $ total. How much $ does Grace have in the end?",
    "ground_truth": 42.0,
    "intermediate_values": [
      35.0,
      21.0,
      42.0
    ],
    "operations": [
      "multiply",
      "derived",
      "derived"
    ],
    "answer_unit": "$"
  },
  {
    "problem_id": "depth03_prob0047",
    "depth": 3,
    "question": "Eve collects $20 per hour and works 4 hours. Eve spends half of Eve's remaining $ on boxes. Eve spends a quarter of Eve's remaining $ on apples. How much $ does Eve have in the end?",
    "ground_truth": 30.0,
    "intermediate_values": [
      80.0,
      40.0,
      30.0
    ],
    "operations": [
      "multiply",
      "derived",
      "derived"
    ],
    "answer_unit": "$"
  },
  {
    "problem_id": "depth03_prob0048",
    "depth": 3,
    "question": "Alice earns $10 per hour and works 6 hours. Alice spends a third of Alice's remaining $ on boxes. Alice then orders 3 books at $8 each. How much $ does Alice have in the end?",
    "ground_truth": 16.0,
    "intermediate_values": [
      60.0,
      40.0,
      16.0
    ],
    "operations": [
      "multiply",
      "derived",
      "derived"
    ],
    "answer_unit": "$"
  },
  {
    "problem_id": "depth03_prob0049",
    "depth": 3,
    "question": "Eve receives $7 per hour and works 9 hours. Eve spends a quarter of Eve's remaining $ on books. A 25% fee is deducted from Eve's total. How much $ does Eve have in the end?",
    "ground_truth": 35.4375,
    "intermediate_values": [
      63.0,
      47.25,
      35.4375
    ],
    "operations": [
      "multiply",
      "derived",
      "derived"
    ],
    "answer_unit": "$"
  },
  {
    "problem_id": "depth03_prob0050",
    "depth": 3,
    "question": "Carlos collects $5 per hour and works 5 hours. Carlos doubles Carlos's current $ total. A 10% fee is deducted from Carlos's total. How much $ does Carlos have in the end?",
    "ground_truth": 45.0,
    "intermediate_values": [
      25.0,
      50.0,
      45.0
    ],
    "operations": [
      "multiply",
      "derived",
      "derived"
    ],
    "answer_unit": "$"
  },
  {
    "problem_id": "depth03_prob0051",
    "depth": 3,
    "question": "Frank gathers $9 per hour and works 3 hours. Frank spends a quarter of Frank's remaining $ on apples. Frank spends $3 on boxes. How much $ does Frank have in the end?",
    "ground_truth": 17.25,
    "intermediate_values": [
      27.0,
      20.25,
      17.25
    ],
    "operations": [
      "multiply",
      "derived",
      "derived"
    ],
    "answer_unit": "$"
  },
  {
    "problem_id": "depth03_prob0052",
    "depth": 3,
    "question": "Alice gathers $16 per hour and works 5 hours. Alice then purchases 5 apples at $7 each. Alice uses $2 on boxes. How much $ does Alice have in the end?",
    "ground_truth": 43.0,
    "intermediate_values": [
      80.0,
      45.0,
      43.0
    ],
    "operations": [
      "multiply",
      "derived",
      "derived"
    ],
    "answer_unit": "$"
  },
  {
    "problem_id": "depth03_prob0053",
    "depth": 3,
    "question": "Diana receives $9 per hour and works 6 hours. Diana gives away $5 on apples. Diana also receives a $6 bonus. How much $ does Diana have in the end?",
    "ground_truth": 55.0,
    "intermediate_values": [
      54.0,
      49.0,
      55.0
    ],
    "operations": [
      "multiply",
      "derived",
      "derived"
    ],
    "answer_unit": "$"
  },
  {
    "problem_id": "depth03_prob0054",
    "depth": 3,
    "question": "Carlos earns $5 per hour and works 8 hours. Carlos spends a quarter of Carlos's remaining $ on apples. Carlos spends half of Carlos's remaining $ on books. How much $ does Carlos have in the end?",
    "ground_truth": 15.0,
    "intermediate_values": [
      40.0,
      30.0,
      15.0
    ],
    "operations": [
      "multiply",
      "derived",
      "derived"
    ],
    "answer_unit": "$"
  },
  {
    "problem_id": "depth03_prob0055",
    "depth": 3,
    "question": "Henry collects $19 per hour and works 8 hours. Henry uses $4 on boxes. Henry then purchases 2 books at $5 each. How much $ does Henry have in the end?",
    "ground_truth": 138.0,
    "intermediate_values": [
      152.0,
      148.0,
      138.0
    ],
    "operations": [
      "multiply",
      "derived",
      "derived"
    ],
    "answer_unit": "$"
  },
  {
    "problem_id": "depth03_prob0056",
    "depth": 3,
    "question": "Bob earns $6 per hour and works 9 hours. Bob spends half of Bob's remaining $ on books. Bob then picks up 2 boxes at $2 each. How much $ does Bob have in the end?",
    "ground_truth": 23.0,
    "intermediate_values": [
      54.0,
      27.0,
      23.0
    ],
    "operations": [
      "multiply",
      "derived",
      "derived"
    ],
    "answer_unit": "$"
  },
  {
    "problem_id": "depth03_prob0057",
    "depth": 3,
    "question": "Carlos gathers $10 per hour and works 4 hours. Carlos spends a third of Carlos's remaining $ on boxes. Carlos donates $7 on apples. How much $ does Carlos have in the end?",
    "ground_truth": 19.666666666666668,
    "intermediate_values": [
      40.0,
      26.666666666666668,
      19.666666666666668
    ],
    "operations": [
      "multiply",
      "derived",
      "derived"
    ],
    "answer_unit": "$"
  },
  {
    "problem_id": "depth03_prob0058",
    "depth": 3,
    "question": "Alice collects $19 per hour and works 3 hours. A 10% fee is deducted from Alice's total. Alice doubles Alice's current $ total. How much $ does Alice have in the end?",
    "ground_truth": 102.6,
    "intermediate_values": [
      57.0,
      51.3,
      102.6
    ],
    "operations": [
      "multiply",
      "derived",
      "derived"
    ],
    "answer_unit": "$"
  },
  {
    "problem_id": "depth03_prob0059",
    "depth": 3,
    "question": "Eve receives $11 per hour and works 4 hours. Eve then picks up 5 books at $2 each. Eve spends a quarter of Eve's remaining $ on boxes. How much $ does Eve have in the end?",
    "ground_truth": 25.5,
    "intermediate_values": [
      44.0,
      34.0,
      25.5
    ],
    "operations": [
      "multiply",
      "derived",
      "derived"
    ],
    "answer_unit": "$"
  },
  {
    "problem_id": "depth03_prob0060",
    "depth": 3,
    "question": "Grace receives $11 per hour and works 7 hours. Grace spends half of Grace's remaining $ on books. A 25% fee is deducted from Grace's total. How much $ does Grace have in the end?",
    "ground_truth": 28.875,
    "intermediate_values": [
      77.0,
      38.5,
      28.875
    ],
    "operations": [
      "multiply",
      "derived",
      "derived"
    ],
    "answer_unit": "$"
  },
  {
    "problem_id": "depth03_prob0061",
    "depth": 3,
    "question": "Frank collects $14 per hour and works 4 hours. Frank doubles Frank's current $ total. Frank uses $2 on books. How much $ does Frank have in the end?",
    "ground_truth": 110.0,
    "intermediate_values": [
      56.0,
      112.0,
      110.0
    ],
    "operations": [
      "multiply",
      "derived",
      "derived"
    ],
    "answer_unit": "$"
  },
  {
    "problem_id": "depth03_prob0062",
    "depth": 3,
    "question": "Carlos gathers $18 per hour and works 6 hours. A 10% fee is deducted from Carlos's total. Carlos spends half of Carlos's remaining $ on books. How much $ does Carlos have in the end?",
    "ground_truth": 48.6,
    "intermediate_values": [
      108.0,
      97.2,
      48.6
    ],
    "operations": [
      "multiply",
      "derived",
      "derived"
    ],
    "answer_unit": "$"
  },
  {
    "problem_id": "depth03_prob0063",
    "depth": 3,
    "question": "Eve gathers $18 per hour and works 4 hours. Eve spends a third of Eve's remaining $ on apples. Eve spends a quarter of Eve's remaining $ on boxes. How much $ does Eve have in the end?",
    "ground_truth": 36.0,
    "intermediate_values": [
      72.0,
      48.0,
      36.0
    ],
    "operations": [
      "multiply",
      "derived",
      "derived"
    ],
    "answer_unit": "$"
  },
  {
    "problem_id": "depth03_prob0064",
    "depth": 3,
    "question": "Grace gathers $18 per hour and works 4 hours. Grace also receives a $15 bonus. Grace spends a third of Grace's remaining $ on apples. How much $ does Grace have in the end?",
    "ground_truth": 58.0,
    "intermediate_values": [
      72.0,
      87.0,
      58.0
    ],
    "operations": [
      "multiply",
      "derived",
      "derived"
    ],
    "answer_unit": "$"
  },
  {
    "problem_id": "depth03_prob0065",
    "depth": 3,
    "question": "Henry gathers $14 per hour and works 10 hours. A 25% fee is deducted from Henry's total. Henry spends a quarter of Henry's remaining $ on apples. How much $ does Henry have in the end?",
    "ground_truth": 78.75,
    "intermediate_values": [
      140.0,
      105.0,
      78.75
    ],
    "operations": [
      "multiply",
      "derived",
      "derived"
    ],
    "answer_unit": "$"
  },
  {
    "problem_id": "depth03_prob0066",
    "depth": 3,
    "question": "Carlos earns $13 per hour and works 9 hours. Carlos then buys 2 books at $7 each. Carlos doubles Carlos's current $ total. How much $ does Carlos have in the end?",
    "ground_truth": 206.0,
    "intermediate_values": [
      117.0,
      103.0,
      206.0
    ],
    "operations": [
      "multiply",
      "derived",
      "derived"
    ],
    "answer_unit": "$"
  },
  {
    "problem_id": "depth03_prob0067",
    "depth": 3,
    "question": "Henry collects $6 per hour and works 3 hours. Henry then orders 3 boxes at $3 each. Henry also receives a $5 bonus. How much $ does Henry have in the end?",
    "ground_truth": 14.0,
    "intermediate_values": [
      18.0,
      9.0,
      14.0
    ],
    "operations": [
      "multiply",
      "derived",
      "derived"
    ],
    "answer_unit": "$"
  },
  {
    "problem_id": "depth03_prob0068",
    "depth": 3,
    "question": "Diana receives $5 per hour and works 6 hours. Diana then purchases 3 books at $2 each. Diana also receives a $14 bonus. How much $ does Diana have in the end?",
    "ground_truth": 38.0,
    "intermediate_values": [
      30.0,
      24.0,
      38.0
    ],
    "operations": [
      "multiply",
      "derived",
      "derived"
    ],
    "answer_unit": "$"
  },
  {
    "problem_id": "depth03_prob0069",
    "depth": 3,
    "question": "Carlos receives $7 per hour and works 9 hours. A 20% fee is deducted from Carlos's total. Carlos spends a third of Carlos's remaining $ on boxes. How much $ does Carlos have in the end?",
    "ground_truth": 33.6,
    "intermediate_values": [
      63.0,
      50.4,
      33.6
    ],
    "operations": [
      "multiply",
      "derived",
      "derived"
    ],
    "answer_unit": "$"
  },
  {
    "problem_id": "depth03_prob0070",
    "depth": 3,
    "question": "Carlos collects $13 per hour and works 6 hours. Carlos spends $6 on books. Carlos spends a third of Carlos's remaining $ on boxes. How much $ does Carlos have in the end?",
    "ground_truth": 48.0,
    "intermediate_values": [
      78.0,
      72.0,
      48.0
    ],
    "operations": [
      "multiply",
      "derived",
      "derived"
    ],
    "answer_unit": "$"
  },
  {
    "problem_id": "depth03_prob0071",
    "depth": 3,
    "question": "Henry collects $8 per hour and works 3 hours. A 20% fee is deducted from Henry's total. Henry then picks up 3 books at $4 each. How much $ does Henry have in the end?",
    "ground_truth": 7.2,
    "intermediate_values": [
      24.0,
      19.2,
      7.2
    ],
    "operations": [
      "multiply",
      "derived",
      "derived"
    ],
    "answer_unit": "$"
  },
  {
    "problem_id": "depth03_prob0072",
    "depth": 3,
    "question": "Eve collects $9 per hour and works 3 hours. Eve spends a quarter of Eve's remaining $ on books. Eve then buys 3 boxes at $3 each. How much $ does Eve have in the end?",
    "ground_truth": 11.25,
    "intermediate_values": [
      27.0,
      20.25,
      11.25
    ],
    "operations": [
      "multiply",
      "derived",
      "derived"
    ],
    "answer_unit": "$"
  },
  {
    "problem_id": "depth03_prob0073",
    "depth": 3,
    "question": "Eve earns $16 per hour and works 6 hours. Eve donates $10 on apples. Eve doubles Eve's current $ total. How much $ does Eve have in the end?",
    "ground_truth": 172.0,
    "intermediate_values": [
      96.0,
      86.0,
      172.0
    ],
    "operations": [
      "multiply",
      "derived",
      "derived"
    ],
    "answer_unit": "$"
  },
  {
    "problem_id": "depth03_prob0074",
    "depth": 3,
    "question": "Diana receives $11 per hour and works 4 hours. Diana also receives a $13 bonus. Diana uses $3 on books. How much $ does Diana have in the end?",
    "ground_truth": 54.0,
    "intermediate_values": [
      44.0,
      57.0,
      54.0
    ],
    "operations": [
      "multiply",
      "derived",
      "derived"
    ],
    "answer_unit": "$"
  },
  {
    "problem_id": "depth03_prob0075",
    "depth": 3,
    "question": "Alice receives $13 per hour and works 6 hours. Alice spends half of Alice's remaining $ on apples. A 25% fee is deducted from Alice's total. How much $ does Alice have in the end?",
    "ground_truth": 29.25,
    "intermediate_values": [
      78.0,
      39.0,
      29.25
    ],
    "operations": [
      "multiply",
      "derived",
      "derived"
    ],
    "answer_unit": "$"
  },
  {
    "problem_id": "depth03_prob0076",
    "depth": 3,
    "question": "Alice collects $10 per hour and works 8 hours. Alice uses $4 on boxes. Alice spends half of Alice's remaining $ on apples. How much $ does Alice have in the end?",
    "ground_truth": 38.0,
    "intermediate_values": [
      80.0,
      76.0,
      38.0
    ],
    "operations": [
      "multiply",
      "derived",
      "derived"
    ],
    "answer_unit": "$"
  },
  {
    "problem_id": "depth03_prob0077",
    "depth": 3,
    "question": "Bob earns $6 per hour and works 10 hours. A 10% fee is deducted from Bob's total. Bob also receives a $8 bonus. How much $ does Bob have in the end?",
    "ground_truth": 62.0,
    "intermediate_values": [
      60.0,
      54.0,
      62.0
    ],
    "operations": [
      "multiply",
      "derived",
      "derived"
    ],
    "answer_unit": "$"
  },
  {
    "problem_id": "depth03_prob0078",
    "depth": 3,
    "question": "Grace collects $10 per hour and works 6 hours. Grace spends $4 on apples. Grace spends a quarter of Grace's remaining $ on boxes. How much $ does Grace have in the end?",
    "ground_truth": 42.0,
    "intermediate_values": [
      60.0,
      56.0,
      42.0
    ],
    "operations": [
      "multiply",
      "derived",
      "derived"
    ],
    "answer_unit": "$"
  },
  {
    "problem_id": "depth03_prob0079",
    "depth": 3,
    "question": "Eve collects $6 per hour and works 7 hours. Eve spends a third of Eve's remaining $ on apples. Eve also receives a $9 bonus. How much $ does Eve have in the end?",
    "ground_truth": 37.0,
    "intermediate_values": [
      42.0,
      28.0,
      37.0
    ],
    "operations": [
      "multiply",
      "derived",
      "derived"
    ],
    "answer_unit": "$"
  },
  {
    "problem_id": "depth03_prob0080",
    "depth": 3,
    "question": "Henry receives $14 per hour and works 7 hours. Henry doubles Henry's current $ total. Henry spends a third of Henry's remaining $ on boxes. How much $ does Henry have in the end?",
    "ground_truth": 130.66666666666666,
    "intermediate_values": [
      98.0,
      196.0,
      130.66666666666666
    ],
    "operations": [
      "multiply",
      "derived",
      "derived"
    ],
    "answer_unit": "$"
  },
  {
    "problem_id": "depth03_prob0081",
    "depth": 3,
    "question": "Diana collects $13 per hour and works 5 hours. A 25% fee is deducted from Diana's total. Diana spends a third of Diana's remaining $ on apples. How much $ does Diana have in the end?",
    "ground_truth": 32.5,
    "intermediate_values": [
      65.0,
      48.75,
      32.5
    ],
    "operations": [
      "multiply",
      "derived",
      "derived"
    ],
    "answer_unit": "$"
  },
  {
    "problem_id": "depth03_prob0082",
    "depth": 3,
    "question": "Eve collects $6 per hour and works 4 hours. Eve spends a third of Eve's remaining $ on boxes. Eve doubles Eve's current $ total. How much $ does Eve have in the end?",
    "ground_truth": 32.0,
    "intermediate_values": [
      24.0,
      16.0,
      32.0
    ],
    "operations": [
      "multiply",
      "derived",
      "derived"
    ],
    "answer_unit": "$"
  },
  {
    "problem_id": "depth03_prob0083",
    "depth": 3,
    "question": "Grace earns $18 per hour and works 5 hours. Grace then buys 4 boxes at $2 each. Grace spends half of Grace's remaining $ on apples. How much $ does Grace have in the end?",
    "ground_truth": 41.0,
    "intermediate_values": [
      90.0,
      82.0,
      41.0
    ],
    "operations": [
      "multiply",
      "derived",
      "derived"
    ],
    "answer_unit": "$"
  },
  {
    "problem_id": "depth03_prob0084",
    "depth": 3,
    "question": "Frank receives $17 per hour and works 8 hours. Frank also receives a $5 bonus. Frank spends a quarter of Frank's remaining $ on books. How much $ does Frank have in the end?",
    "ground_truth": 105.75,
    "intermediate_values": [
      136.0,
      141.0,
      105.75
    ],
    "operations": [
      "multiply",
      "derived",
      "derived"
    ],
    "answer_unit": "$"
  },
  {
    "problem_id": "depth03_prob0085",
    "depth": 3,
    "question": "Bob gathers $5 per hour and works 8 hours. Bob spends a third of Bob's remaining $ on books. A 25% fee is deducted from Bob's total. How much $ does Bob have in the end?",
    "ground_truth": 20.0,
    "intermediate_values": [
      40.0,
      26.666666666666668,
      20.0
    ],
    "operations": [
      "multiply",
      "derived",
      "derived"
    ],
    "answer_unit": "$"
  },
  {
    "problem_id": "depth03_prob0086",
    "depth": 3,
    "question": "Eve collects $8 per hour and works 9 hours. Eve spends a quarter of Eve's remaining $ on boxes. Eve spends a third of Eve's remaining $ on books. How much $ does Eve have in the end?",
    "ground_truth": 36.0,
    "intermediate_values": [
      72.0,
      54.0,
      36.0
    ],
    "operations": [
      "multiply",
      "derived",
      "derived"
    ],
    "answer_unit": "$"
  },
  {
    "problem_id": "depth03_prob0087",
    "depth": 3,
    "question": "Frank gathers $11 per hour and works 10 hours. Frank uses $6 on apples. Frank then buys 3 boxes at $4 each. How much $ does Frank have in the end?",
    "ground_truth": 92.0,
    "intermediate_values": [
      110.0,
      104.0,
      92.0
    ],
    "operations": [
      "multiply",
      "derived",
      "derived"
    ],
    "answer_unit": "$"
  },
  {
    "problem_id": "depth03_prob0088",
    "depth": 3,
    "question": "Diana gathers $18 per hour and works 6 hours. Diana spends half of Diana's remaining $ on books. Diana doubles Diana's current $ total. How much $ does Diana have in the end?",
    "ground_truth": 108.0,
    "intermediate_values": [
      108.0,
      54.0,
      108.0
    ],
    "operations": [
      "multiply",
      "derived",
      "derived"
    ],
    "answer_unit": "$"
  },
  {
    "problem_id": "depth03_prob0089",
    "depth": 3,
    "question": "Bob earns $10 per hour and works 6 hours. Bob doubles Bob's current $ total. Bob gives away $5 on boxes. How much $ does Bob have in the end?",
    "ground_truth": 115.0,
    "intermediate_values": [
      60.0,
      120.0,
      115.0
    ],
    "operations": [
      "multiply",
      "derived",
      "derived"
    ],
    "answer_unit": "$"
  },
  {
    "problem_id": "depth03_prob0090",
    "depth": 3,
    "question": "Diana collects $18 per hour and works 4 hours. A 10% fee is deducted from Diana's total. Diana also receives a $13 bonus. How much $ does Diana have in the end?",
    "ground_truth": 77.8,
    "intermediate_values": [
      72.0,
      64.8,
      77.8
    ],
    "operations": [
      "multiply",
      "derived",
      "derived"
    ],
    "answer_unit": "$"
  },
  {
    "problem_id": "depth03_prob0091",
    "depth": 3,
    "question": "Grace receives $17 per hour and works 3 hours. A 10% fee is deducted from Grace's total. Grace spends a quarter of Grace's remaining $ on boxes. How much $ does Grace have in the end?",
    "ground_truth": 34.425,
    "intermediate_values": [
      51.0,
      45.9,
      34.425
    ],
    "operations": [
      "multiply",
      "derived",
      "derived"
    ],
    "answer_unit": "$"
  },
  {
    "problem_id": "depth03_prob0092",
    "depth": 3,
    "question": "Diana receives $7 per hour and works 5 hours. Diana also receives a $11 bonus. Diana spends a third of Diana's remaining $ on books. How much $ does Diana have in the end?",
    "ground_truth": 30.666666666666668,
    "intermediate_values": [
      35.0,
      46.0,
      30.666666666666668
    ],
    "operations": [
      "multiply",
      "derived",
      "derived"
    ],
    "answer_unit": "$"
  },
  {
    "problem_id": "depth03_prob0093",
    "depth": 3,
    "question": "Carlos collects $19 per hour and works 3 hours. Carlos then purchases 5 books at $3 each. Carlos spends a third of Carlos's remaining $ on boxes. How much $ does Carlos have in the end?",
    "ground_truth": 28.0,
    "intermediate_values": [
      57.0,
      42.0,
      28.0
    ],
    "operations": [
      "multiply",
      "derived",
      "derived"
    ],
    "answer_unit": "$"
  },
  {
    "problem_id": "depth03_prob0094",
    "depth": 3,
    "question": "Grace earns $5 per hour and works 9 hours. Grace spends a quarter of Grace's remaining $ on boxes. Grace donates $3 on apples. How much $ does Grace have in the end?",
    "ground_truth": 30.75,
    "intermediate_values": [
      45.0,
      33.75,
      30.75
    ],
    "operations": [
      "multiply",
      "derived",
      "derived"
    ],
    "answer_unit": "$"
  },
  {
    "problem_id": "depth03_prob0095",
    "depth": 3,
    "question": "Frank earns $14 per hour and works 6 hours. Frank spends a third of Frank's remaining $ on boxes. Frank spends half of Frank's remaining $ on apples. How much $ does Frank have in the end?",
    "ground_truth": 28.0,
    "intermediate_values": [
      84.0,
      56.0,
      28.0
    ],
    "operations": [
      "multiply",
      "derived",
      "derived"
    ],
    "answer_unit": "$"
  },
  {
    "problem_id": "depth03_prob0096",
    "depth": 3,
    "question": "Eve receives $18 per hour and works 8 hours. Eve spends half of Eve's remaining $ on books. Eve doubles Eve's current $ total. How much $ does Eve have in the end?",
    "ground_truth": 144.0,
    "intermediate_values": [
      144.0,
      72.0,
      144.0
    ],
    "operations": [
      "multiply",
      "derived",
      "derived"
    ],
    "answer_unit": "$"
  },
  {
    "problem_id": "depth03_prob0097",
    "depth": 3,
    "question": "Frank earns $12 per hour and works 3 hours. Frank doubles Frank's current $ total. Frank then orders 5 apples at $6 each. How much $ does Frank have in the end?",
    "ground_truth": 42.0,
    "intermediate_values": [
      36.0,
      72.0,
      42.0
    ],
    "operations": [
      "multiply",
      "derived",
      "derived"
    ],
    "answer_unit": "$"
  },
  {
    "problem_id": "depth03_prob0098",
    "depth": 3,
    "question": "Bob receives $6 per hour and works 6 hours. Bob spends half of Bob's remaining $ on apples. Bob gives away $9 on boxes. How much $ does Bob have in the end?",
    "ground_truth": 9.0,
    "intermediate_values": [
      36.0,
      18.0,
      9.0
    ],
    "operations": [
      "multiply",
      "derived",
      "derived"
    ],
    "answer_unit": "$"
  },
  {
    "problem_id": "depth03_prob0099",
    "depth": 3,
    "question": "Bob gathers $14 per hour and works 10 hours. Bob spends a quarter of Bob's remaining $ on books. Bob spends half of Bob's remaining $ on boxes. How much $ does Bob have in the end?",
    "ground_truth": 52.5,
    "intermediate_values": [
      140.0,
      105.0,
      52.5
    ],
    "operations": [
      "multiply",
      "derived",
      "derived"
    ],
    "answer_unit": "$"
  },
  {
    "problem_id": "depth03_prob0100",
    "depth": 3,
    "question": "Eve earns $18 per hour and works 6 hours. Eve gives away $2 on apples. Eve spends a third of Eve's remaining $ on books. How much $ does Eve have in the end?",
    "ground_truth": 70.66666666666667,
    "intermediate_values": [
      108.0,
      106.0,
      70.66666666666667
    ],
    "operations": [
      "multiply",
      "derived",
      "derived"
    ],
    "answer_unit": "$"
  },
  {
    "problem_id": "depth03_prob0101",
    "depth": 3,
    "question": "Carlos gathers $10 per hour and works 10 hours. Carlos donates $10 on apples. Carlos spends a quarter of Carlos's remaining $ on books. How much $ does Carlos have in the end?",
    "ground_truth": 67.5,
    "intermediate_values": [
      100.0,
      90.0,
      67.5
    ],
    "operations": [
      "multiply",
      "derived",
      "derived"
    ],
    "answer_unit": "$"
  },
  {
    "problem_id": "depth03_prob0102",
    "depth": 3,
    "question": "Grace earns $8 per hour and works 10 hours. Grace doubles Grace's current $ total. Grace also receives a $15 bonus. How much $ does Grace have in the end?",
    "ground_truth": 175.0,
    "intermediate_values": [
      80.0,
      160.0,
      175.0
    ],
    "operations": [
      "multiply",
      "derived",
      "derived"
    ],
    "answer_unit": "$"
  },
  {
    "problem_id": "depth03_prob0103",
    "depth": 3,
    "question": "Grace collects $18 per hour and works 10 hours. Grace then purchases 4 boxes at $3 each. Grace spends a quarter of Grace's remaining $ on apples. How much $ does Grace have in the end?",
    "ground_truth": 126.0,
    "intermediate_values": [
      180.0,
      168.0,
      126.0
    ],
    "operations": [
      "multiply",
      "derived",
      "derived"
    ],
    "answer_unit": "$"
  },
  {
    "problem_id": "depth03_prob0104",
    "depth": 3,
    "question": "Carlos receives $19 per hour and works 3 hours. Carlos spends $5 on boxes. Carlos spends half of Carlos's remaining $ on books. How much $ does Carlos have in the end?",
    "ground_truth": 26.0,
    "intermediate_values": [
      57.0,
      52.0,
      26.0
    ],
    "operations": [
      "multiply",
      "derived",
      "derived"
    ],
    "answer_unit": "$"
  },
  {
    "problem_id": "depth03_prob0105",
    "depth": 3,
    "question": "Frank earns $18 per hour and works 9 hours. A 20% fee is deducted from Frank's total. Frank also receives a $13 bonus. How much $ does Frank have in the end?",
    "ground_truth": 142.6,
    "intermediate_values": [
      162.0,
      129.6,
      142.6
    ],
    "operations": [
      "multiply",
      "derived",
      "derived"
    ],
    "answer_unit": "$"
  },
  {
    "problem_id": "depth03_prob0106",
    "depth": 3,
    "question": "Bob receives $19 per hour and works 7 hours. A 25% fee is deducted from Bob's total. Bob then purchases 5 boxes at $6 each. How much $ does Bob have in the end?",
    "ground_truth": 69.75,
    "intermediate_values": [
      133.0,
      99.75,
      69.75
    ],
    "operations": [
      "multiply",
      "derived",
      "derived"
    ],
    "answer_unit": "$"
  },
  {
    "problem_id": "depth03_prob0107",
    "depth": 3,
    "question": "Eve gathers $15 per hour and works 10 hours. Eve spends a third of Eve's remaining $ on apples. Eve then buys 3 books at $7 each. How much $ does Eve have in the end?",
    "ground_truth": 79.0,
    "intermediate_values": [
      150.0,
      100.0,
      79.0
    ],
    "operations": [
      "multiply",
      "derived",
      "derived"
    ],
    "answer_unit": "$"
  },
  {
    "problem_id": "depth03_prob0108",
    "depth": 3,
    "question": "Carlos gathers $16 per hour and works 6 hours. Carlos doubles Carlos's current $ total. Carlos also receives a $13 bonus. How much $ does Carlos have in the end?",
    "ground_truth": 205.0,
    "intermediate_values": [
      96.0,
      192.0,
      205.0
    ],
    "operations": [
      "multiply",
      "derived",
      "derived"
    ],
    "answer_unit": "$"
  },
  {
    "problem_id": "depth03_prob0109",
    "depth": 3,
    "question": "Diana gathers $19 per hour and works 7 hours. Diana spends $4 on apples. Diana doubles Diana's current $ total. How much $ does Diana have in the end?",
    "ground_truth": 258.0,
    "intermediate_values": [
      133.0,
      129.0,
      258.0
    ],
    "operations": [
      "multiply",
      "derived",
      "derived"
    ],
    "answer_unit": "$"
  },
  {
    "problem_id": "depth03_prob0110",
    "depth": 3,
    "question": "Eve collects $17 per hour and works 8 hours. Eve also receives a $6 bonus. Eve spends a third of Eve's remaining $ on boxes. How much $ does Eve have in the end?",
    "ground_truth": 94.66666666666667,
    "intermediate_values": [
      136.0,
      142.0,
      94.66666666666667
    ],
    "operations": [
      "multiply",
      "derived",
      "derived"
    ],
    "answer_unit": "$"
  },
  {
    "problem_id": "depth03_prob0111",
    "depth": 3,
    "question": "Carlos earns $18 per hour and works 3 hours. Carlos spends half of Carlos's remaining $ on books. Carlos then buys 3 apples at $2 each. How much $ does Carlos have in the end?",
    "ground_truth": 21.0,
    "intermediate_values": [
      54.0,
      27.0,
      21.0
    ],
    "operations": [
      "multiply",
      "derived",
      "derived"
    ],
    "answer_unit": "$"
  },
  {
    "problem_id": "depth03_prob0112",
    "depth": 3,
    "question": "Eve gathers $17 per hour and works 5 hours. A 10% fee is deducted from Eve's total. Eve doubles Eve's current $ total. How much $ does Eve have in the end?",
    "ground_truth": 153.0,
    "intermediate_values": [
      85.0,
      76.5,
      153.0
    ],
    "operations": [
      "multiply",
      "derived",
      "derived"
    ],
    "answer_unit": "$"
  },
  {
    "problem_id": "depth03_prob0113",
    "depth": 3,
    "question": "Carlos receives $19 per hour and works 5 hours. Carlos also receives a $13 bonus. Carlos then buys 2 books at $3 each. How much $ does Carlos have in the end?",
    "ground_truth": 102.0,
    "intermediate_values": [
      95.0,
      108.0,
      102.0
    ],
    "operations": [
      "multiply",
      "derived",
      "derived"
    ],
    "answer_unit": "$"
  },
  {
    "problem_id": "depth03_prob0114",
    "depth": 3,
    "question": "Frank gathers $17 per hour and works 9 hours. Frank spends a third of Frank's remaining $ on apples. A 25% fee is deducted from Frank's total. How much $ does Frank have in the end?",
    "ground_truth": 76.5,
    "intermediate_values": [
      153.0,
      102.0,
      76.5
    ],
    "operations": [
      "multiply",
      "derived",
      "derived"
    ],
    "answer_unit": "$"
  },
  {
    "problem_id": "depth03_prob0115",
    "depth": 3,
    "question": "Henry earns $19 per hour and works 9 hours. Henry doubles Henry's current $ total. Henry spends a third of Henry's remaining $ on apples. How much $ does Henry have in the end?",
    "ground_truth": 228.0,
    "intermediate_values": [
      171.0,
      342.0,
      228.0
    ],
    "operations": [
      "multiply",
      "derived",
      "derived"
    ],
    "answer_unit": "$"
  },
  {
    "problem_id": "depth03_prob0116",
    "depth": 3,
    "question": "Diana collects $9 per hour and works 10 hours. Diana spends a quarter of Diana's remaining $ on boxes. A 25% fee is deducted from Diana's total. How much $ does Diana have in the end?",
    "ground_truth": 50.625,
    "intermediate_values": [
      90.0,
      67.5,
      50.625
    ],
    "operations": [
      "multiply",
      "derived",
      "derived"
    ],
    "answer_unit": "$"
  },
  {
    "problem_id": "depth03_prob0117",
    "depth": 3,
    "question": "Bob receives $13 per hour and works 7 hours. Bob spends a quarter of Bob's remaining $ on boxes. Bob also receives a $8 bonus. How much $ does Bob have in the end?",
    "ground_truth": 76.25,
    "intermediate_values": [
      91.0,
      68.25,
      76.25
    ],
    "operations": [
      "multiply",
      "derived",
      "derived"
    ],
    "answer_unit": "$"
  },
  {
    "problem_id": "depth03_prob0118",
    "depth": 3,
    "question": "Alice collects $13 per hour and works 4 hours. Alice also receives a $6 bonus. A 10% fee is deducted from Alice's total. How much $ does Alice have in the end?",
    "ground_truth": 52.2,
    "intermediate_values": [
      52.0,
      58.0,
      52.2
    ],
    "operations": [
      "multiply",
      "derived",
      "derived"
    ],
    "answer_unit": "$"
  },
  {
    "problem_id": "depth03_prob0119",
    "depth": 3,
    "question": "Henry gathers $9 per hour and works 10 hours. A 20% fee is deducted from Henry's total. Henry also receives a $15 bonus. How much $ does Henry have in the end?",
    "ground_truth": 87.0,
    "intermediate_values": [
      90.0,
      72.0,
      87.0
    ],
    "operations": [
      "multiply",
      "derived",
      "derived"
    ],
    "answer_unit": "$"
  },
  {
    "problem_id": "depth03_prob0120",
    "depth": 3,
    "question": "Diana earns $19 per hour and works 4 hours. Diana also receives a $15 bonus. Diana doubles Diana's current $ total. How much $ does Diana have in the end?",
    "ground_truth": 182.0,
    "intermediate_values": [
      76.0,
      91.0,
      182.0
    ],
    "operations": [
      "multiply",
      "derived",
      "derived"
    ],
    "answer_unit": "$"
  },
  {
    "problem_id": "depth03_prob0121",
    "depth": 3,
    "question": "Alice gathers $15 per hour and works 8 hours. Alice doubles Alice's current $ total. Alice also receives a $15 bonus. How much $ does Alice have in the end?",
    "ground_truth": 255.0,
    "intermediate_values": [
      120.0,
      240.0,
      255.0
    ],
    "operations": [
      "multiply",
      "derived",
      "derived"
    ],
    "answer_unit": "$"
  },
  {
    "problem_id": "depth03_prob0122",
    "depth": 3,
    "question": "Alice gathers $14 per hour and works 8 hours. Alice gives away $3 on boxes. A 25% fee is deducted from Alice's total. How much $ does Alice have in the end?",
    "ground_truth": 81.75,
    "intermediate_values": [
      112.0,
      109.0,
      81.75
    ],
    "operations": [
      "multiply",
      "derived",
      "derived"
    ],
    "answer_unit": "$"
  },
  {
    "problem_id": "depth03_prob0123",
    "depth": 3,
    "question": "Diana receives $16 per hour and works 4 hours. Diana spends a quarter of Diana's remaining $ on apples. Diana then purchases 3 boxes at $7 each. How much $ does Diana have in the end?",
    "ground_truth": 27.0,
    "intermediate_values": [
      64.0,
      48.0,
      27.0
    ],
    "operations": [
      "multiply",
      "derived",
      "derived"
    ],
    "answer_unit": "$"
  },
  {
    "problem_id": "depth03_prob0124",
    "depth": 3,
    "question": "Frank collects $11 per hour and works 9 hours. Frank spends half of Frank's remaining $ on boxes. Frank spends a quarter of Frank's remaining $ on apples. How much $ does Frank have in the end?",
    "ground_truth": 37.125,
    "intermediate_values": [
      99.0,
      49.5,
      37.125
    ],
    "operations": [
      "multiply",
      "derived",
      "derived"
    ],
    "answer_unit": "$"
  },
  {
    "problem_id": "depth03_prob0125",
    "depth": 3,
    "question": "Grace receives $20 per hour and works 9 hours. Grace donates $5 on books. Grace doubles Grace's current $ total. How much $ does Grace have in the end?",
    "ground_truth": 350.0,
    "intermediate_values": [
      180.0,
      175.0,
      350.0
    ],
    "operations": [
      "multiply",
      "derived",
      "derived"
    ],
    "answer_unit": "$"
  },
  {
    "problem_id": "depth03_prob0126",
    "depth": 3,
    "question": "Grace gathers $15 per hour and works 7 hours. Grace spends half of Grace's remaining $ on books. Grace spends a third of Grace's remaining $ on boxes. How much $ does Grace have in the end?",
    "ground_truth": 35.0,
    "intermediate_values": [
      105.0,
      52.5,
      35.0
    ],
    "operations": [
      "multiply",
      "derived",
      "derived"
    ],
    "answer_unit": "$"
  },
  {
    "problem_id": "depth03_prob0127",
    "depth": 3,
    "question": "Alice earns $8 per hour and works 10 hours. Alice also receives a $12 bonus. Alice spends a third of Alice's remaining $ on apples. How much $ does Alice have in the end?",
    "ground_truth": 61.333333333333336,
    "intermediate_values": [
      80.0,
      92.0,
      61.333333333333336
    ],
    "operations": [
      "multiply",
      "derived",
      "derived"
    ],
    "answer_unit": "$"
  },
  {
    "problem_id": "depth03_prob0128",
    "depth": 3,
    "question": "Carlos collects $19 per hour and works 3 hours. Carlos doubles Carlos's current $ total. Carlos spends a quarter of Carlos's remaining $ on apples. How much $ does Carlos have in the end?",
    "ground_truth": 85.5,
    "intermediate_values": [
      57.0,
      114.0,
      85.5
    ],
    "operations": [
      "multiply",
      "derived",
      "derived"
    ],
    "answer_unit": "$"
  },
  {
    "problem_id": "depth03_prob0129",
    "depth": 3,
    "question": "Eve gathers $10 per hour and works 9 hours. Eve spends half of Eve's remaining $ on apples. Eve doubles Eve's current $ total. How much $ does Eve have in the end?",
    "ground_truth": 90.0,
    "intermediate_values": [
      90.0,
      45.0,
      90.0
    ],
    "operations": [
      "multiply",
      "derived",
      "derived"
    ],
    "answer_unit": "$"
  },
  {
    "problem_id": "depth03_prob0130",
    "depth": 3,
    "question": "Frank earns $14 per hour and works 6 hours. Frank spends a quarter of Frank's remaining $ on boxes. A 20% fee is deducted from Frank's total. How much $ does Frank have in the end?",
    "ground_truth": 50.4,
    "intermediate_values": [
      84.0,
      63.0,
      50.4
    ],
    "operations": [
      "multiply",
      "derived",
      "derived"
    ],
    "answer_unit": "$"
  },
  {
    "problem_id": "depth03_prob0131",
    "depth": 3,
    "question": "Henry collects $20 per hour and works 4 hours. Henry spends half of Henry's remaining $ on books. Henry then picks up 4 apples at $8 each. How much $ does Henry have in the end?",
    "ground_truth": 8.0,
    "intermediate_values": [
      80.0,
      40.0,
      8.0
    ],
    "operations": [
      "multiply",
      "derived",
      "derived"
    ],
    "answer_unit": "$"
  },
  {
    "problem_id": "depth03_prob0132",
    "depth": 3,
    "question": "Grace collects $18 per hour and works 5 hours. Grace spends a third of Grace's remaining $ on boxes. A 25% fee is deducted from Grace's total. How much $ does Grace have in the end?",
    "ground_truth": 45.0,
    "intermediate_values": [
      90.0,
      60.0,
      45.0
    ],
    "operations": [
      "multiply",
      "derived",
      "derived"
    ],
    "answer_unit": "$"
  },
  {
    "problem_id": "depth03_prob0133",
    "depth": 3,
    "question": "Alice earns $8 per hour and works 10 hours. A 25% fee is deducted from Alice's total. Alice spends $9 on apples. How much $ does Alice have in the end?",
    "ground_truth": 51.0,
    "intermediate_values": [
      80.0,
      60.0,
      51.0
    ],
    "operations": [
      "multiply",
      "derived",
      "derived"
    ],
    "answer_unit": "$"
  },
  {
    "problem_id": "depth03_prob0134",
    "depth": 3,
    "question": "Alice receives $20 per hour and works 3 hours. Alice then orders 4 books at $7 each. Alice donates $4 on boxes. How much $ does Alice have in the end?",
    "ground_truth": 28.0,
    "intermediate_values": [
      60.0,
      32.0,
      28.0
    ],
    "operations": [
      "multiply",
      "derived",
      "derived"
    ],
    "answer_unit": "$"
  },
  {
    "problem_id": "depth03_prob0135",
    "depth": 3,
    "question": "Carlos gathers $16 per hour and works 3 hours. Carlos spends a third of Carlos's remaining $ on boxes. Carlos doubles Carlos's current $ total. How much $ does Carlos have in the end?",
    "ground_truth": 64.0,
    "intermediate_values": [
      48.0,
      32.0,
      64.0
    ],
    "operations": [
      "multiply",
      "derived",
      "derived"
    ],
    "answer_unit": "$"
  },
  {
    "problem_id": "depth03_prob0136",
    "depth": 3,
    "question": "Carlos earns $20 per hour and works 10 hours. Carlos spends a third of Carlos's remaining $ on boxes. Carlos doubles Carlos's current $ total. How much $ does Carlos have in the end?",
    "ground_truth": 266.6666666666667,
    "intermediate_values": [
      200.0,
      133.33333333333334,
      266.6666666666667
    ],
    "operations": [
      "multiply",
      "derived",
      "derived"
    ],
    "answer_unit": "$"
  },
  {
    "problem_id": "depth03_prob0137",
    "depth": 3,
    "question": "Alice collects $12 per hour and works 4 hours. Alice spends a third of Alice's remaining $ on apples. Alice also receives a $10 bonus. How much $ does Alice have in the end?",
    "ground_truth": 42.0,
    "intermediate_values": [
      48.0,
      32.0,
      42.0
    ],
    "operations": [
      "multiply",
      "derived",
      "derived"
    ],
    "answer_unit": "$"
  },
  {
    "problem_id": "depth03_prob0138",
    "depth": 3,
    "question": "Alice earns $6 per hour and works 6 hours. A 25% fee is deducted from Alice's total. Alice spends a third of Alice's remaining $ on apples. How much $ does Alice have in the end?",
    "ground_truth": 18.0,
    "intermediate_values": [
      36.0,
      27.0,
      18.0
    ],
    "operations": [
      "multiply",
      "derived",
      "derived"
    ],
    "answer_unit": "$"
  },
  {
    "problem_id": "depth03_prob0139",
    "depth": 3,
    "question": "Henry gathers $18 per hour and works 8 hours. A 10% fee is deducted from Henry's total. Henry spends $5 on books. How much $ does Henry have in the end?",
    "ground_truth": 124.6,
    "intermediate_values": [
      144.0,
      129.6,
      124.6
    ],
    "operations": [
      "multiply",
      "derived",
      "derived"
    ],
    "answer_unit": "$"
  },
  {
    "problem_id": "depth03_prob0140",
    "depth": 3,
    "question": "Diana earns $14 per hour and works 6 hours. Diana spends a quarter of Diana's remaining $ on books. Diana then picks up 4 boxes at $6 each. How much $ does Diana have in the end?",
    "ground_truth": 39.0,
    "intermediate_values": [
      84.0,
      63.0,
      39.0
    ],
    "operations": [
      "multiply",
      "derived",
      "derived"
    ],
    "answer_unit": "$"
  },
  {
    "problem_id": "depth03_prob0141",
    "depth": 3,
    "question": "Diana earns $10 per hour and works 6 hours. A 20% fee is deducted from Diana's total. Diana spends a third of Diana's remaining $ on apples. How much $ does Diana have in the end?",
    "ground_truth": 32.0,
    "intermediate_values": [
      60.0,
      48.0,
      32.0
    ],
    "operations": [
      "multiply",
      "derived",
      "derived"
    ],
    "answer_unit": "$"
  },
  {
    "problem_id": "depth03_prob0142",
    "depth": 3,
    "question": "Grace earns $16 per hour and works 5 hours. Grace spends half of Grace's remaining $ on books. Grace spends a quarter of Grace's remaining $ on apples. How much $ does Grace have in the end?",
    "ground_truth": 30.0,
    "intermediate_values": [
      80.0,
      40.0,
      30.0
    ],
    "operations": [
      "multiply",
      "derived",
      "derived"
    ],
    "answer_unit": "$"
  },
  {
    "problem_id": "depth03_prob0143",
    "depth": 3,
    "question": "Grace collects $5 per hour and works 10 hours. Grace also receives a $6 bonus. Grace doubles Grace's current $ total. How much $ does Grace have in the end?",
    "ground_truth": 112.0,
    "intermediate_values": [
      50.0,
      56.0,
      112.0
    ],
    "operations": [
      "multiply",
      "derived",
      "derived"
    ],
    "answer_unit": "$"
  },
  {
    "problem_id": "depth03_prob0144",
    "depth": 3,
    "question": "Grace gathers $14 per hour and works 4 hours. Grace also receives a $10 bonus. Grace then picks up 4 boxes at $2 each. How much $ does Grace have in the end?",
    "ground_truth": 58.0,
    "intermediate_values": [
      56.0,
      66.0,
      58.0
    ],
    "operations": [
      "multiply",
      "derived",
      "derived"
    ],
    "answer_unit": "$"
  },
  {
    "problem_id": "depth03_prob0145",
    "depth": 3,
    "question": "Carlos earns $19 per hour and works 8 hours. Carlos doubles Carlos's current $ total. Carlos spends half of Carlos's remaining $ on books. How much $ does Carlos have in the end?",
    "ground_truth": 152.0,
    "intermediate_values": [
      152.0,
      304.0,
      152.0
    ],
    "operations": [
      "multiply",
      "derived",
      "derived"
    ],
    "answer_unit": "$"
  },
  {
    "problem_id": "depth03_prob0146",
    "depth": 3,
    "question": "Grace collects $10 per hour and works 9 hours. Grace also receives a $13 bonus. A 25% fee is deducted from Grace's total. How much $ does Grace have in the end?",
    "ground_truth": 77.25,
    "intermediate_values": [
      90.0,
      103.0,
      77.25
    ],
    "operations": [
      "multiply",
      "derived",
      "derived"
    ],
    "answer_unit": "$"
  },
  {
    "problem_id": "depth03_prob0147",
    "depth": 3,
    "question": "Henry receives $14 per hour and works 8 hours. Henry spends half of Henry's remaining $ on apples. Henry spends a third of Henry's remaining $ on boxes. How much $ does Henry have in the end?",
    "ground_truth": 37.333333333333336,
    "intermediate_values": [
      112.0,
      56.0,
      37.333333333333336
    ],
    "operations": [
      "multiply",
      "derived",
      "derived"
    ],
    "answer_unit": "$"
  },
  {
    "problem_id": "depth03_prob0148",
    "depth": 3,
    "question": "Alice earns $10 per hour and works 5 hours. Alice spends a third of Alice's remaining $ on books. Alice doubles Alice's current $ total. How much $ does Alice have in the end?",
    "ground_truth": 66.66666666666667,
    "intermediate_values": [
      50.0,
      33.333333333333336,
      66.66666666666667
    ],
    "operations": [
      "multiply",
      "derived",
      "derived"
    ],
    "answer_unit": "$"
  },
  {
    "problem_id": "depth03_prob0149",
    "depth": 3,
    "question": "Diana collects $5 per hour and works 4 hours. Diana doubles Diana's current $ total. Diana also receives a $5 bonus. How much $ does Diana have in the end?",
    "ground_truth": 45.0,
    "intermediate_values": [
      20.0,
      40.0,
      45.0
    ],
    "operations": [
      "multiply",
      "derived",
      "derived"
    ],
    "answer_unit": "$"
  },
  {
    "problem_id": "depth03_prob0150",
    "depth": 3,
    "question": "Bob earns $10 per hour and works 4 hours. Bob also receives a $5 bonus. Bob spends a quarter of Bob's remaining $ on apples. How much $ does Bob have in the end?",
    "ground_truth": 33.75,
    "intermediate_values": [
      40.0,
      45.0,
      33.75
    ],
    "operations": [
      "multiply",
      "derived",
      "derived"
    ],
    "answer_unit": "$"
  },
  {
    "problem_id": "depth03_prob0151",
    "depth": 3,
    "question": "Grace collects $12 per hour and works 8 hours. Grace doubles Grace's current $ total. Grace then orders 4 apples at $7 each. How much $ does Grace have in the end?",
    "ground_truth": 164.0,
    "intermediate_values": [
      96.0,
      192.0,
      164.0
    ],
    "operations": [
      "multiply",
      "derived",
      "derived"
    ],
    "answer_unit": "$"
  },
  {
    "problem_id": "depth03_prob0152",
    "depth": 3,
    "question": "Alice earns $18 per hour and works 7 hours. Alice spends a quarter of Alice's remaining $ on boxes. A 20% fee is deducted from Alice's total. How much $ does Alice have in the end?",
    "ground_truth": 75.6,
    "intermediate_values": [
      126.0,
      94.5,
      75.6
    ],
    "operations": [
      "multiply",
      "derived",
      "derived"
    ],
    "answer_unit": "$"
  },
  {
    "problem_id": "depth03_prob0153",
    "depth": 3,
    "question": "Carlos earns $13 per hour and works 10 hours. A 25% fee is deducted from Carlos's total. Carlos doubles Carlos's current $ total. How much $ does Carlos have in the end?",
    "ground_truth": 195.0,
    "intermediate_values": [
      130.0,
      97.5,
      195.0
    ],
    "operations": [
      "multiply",
      "derived",
      "derived"
    ],
    "answer_unit": "$"
  },
  {
    "problem_id": "depth03_prob0154",
    "depth": 3,
    "question": "Frank collects $14 per hour and works 8 hours. Frank spends a third of Frank's remaining $ on books. Frank also receives a $12 bonus. How much $ does Frank have in the end?",
    "ground_truth": 86.66666666666667,
    "intermediate_values": [
      112.0,
      74.66666666666667,
      86.66666666666667
    ],
    "operations": [
      "multiply",
      "derived",
      "derived"
    ],
    "answer_unit": "$"
  },
  {
    "problem_id": "depth03_prob0155",
    "depth": 3,
    "question": "Diana receives $16 per hour and works 9 hours. Diana also receives a $14 bonus. Diana uses $6 on boxes. How much $ does Diana have in the end?",
    "ground_truth": 152.0,
    "intermediate_values": [
      144.0,
      158.0,
      152.0
    ],
    "operations": [
      "multiply",
      "derived",
      "derived"
    ],
    "answer_unit": "$"
  },
  {
    "problem_id": "depth03_prob0156",
    "depth": 3,
    "question": "Frank collects $9 per hour and works 6 hours. Frank spends a quarter of Frank's remaining $ on boxes. Frank also receives a $5 bonus. How much $ does Frank have in the end?",
    "ground_truth": 45.5,
    "intermediate_values": [
      54.0,
      40.5,
      45.5
    ],
    "operations": [
      "multiply",
      "derived",
      "derived"
    ],
    "answer_unit": "$"
  },
  {
    "problem_id": "depth03_prob0157",
    "depth": 3,
    "question": "Henry receives $17 per hour and works 4 hours. A 25% fee is deducted from Henry's total. Henry also receives a $12 bonus. How much $ does Henry have in the end?",
    "ground_truth": 63.0,
    "intermediate_values": [
      68.0,
      51.0,
      63.0
    ],
    "operations": [
      "multiply",
      "derived",
      "derived"
    ],
    "answer_unit": "$"
  },
  {
    "problem_id": "depth03_prob0158",
    "depth": 3,
    "question": "Diana receives $6 per hour and works 4 hours. Diana then purchases 2 apples at $2 each. A 10% fee is deducted from Diana's total. How much $ does Diana have in the end?",
    "ground_truth": 18.0,
    "intermediate_values": [
      24.0,
      20.0,
      18.0
    ],
    "operations": [
      "multiply",
      "derived",
      "derived"
    ],
    "answer_unit": "$"
  },
  {
    "problem_id": "depth03_prob0159",
    "depth": 3,
    "question": "Alice earns $8 per hour and works 7 hours. Alice also receives a $6 bonus. Alice gives away $7 on boxes. How much $ does Alice have in the end?",
    "ground_truth": 55.0,
    "intermediate_values": [
      56.0,
      62.0,
      55.0
    ],
    "operations": [
      "multiply",
      "derived",
      "derived"
    ],
    "answer_unit": "$"
  },
  {
    "problem_id": "depth03_prob0160",
    "depth": 3,
    "question": "Henry earns $12 per hour and works 8 hours. Henry doubles Henry's current $ total. Henry gives away $4 on books. How much $ does Henry have in the end?",
    "ground_truth": 188.0,
    "intermediate_values": [
      96.0,
      192.0,
      188.0
    ],
    "operations": [
      "multiply",
      "derived",
      "derived"
    ],
    "answer_unit": "$"
  },
  {
    "problem_id": "depth03_prob0161",
    "depth": 3,
    "question": "Eve gathers $18 per hour and works 7 hours. Eve doubles Eve's current $ total. A 10% fee is deducted from Eve's total. How much $ does Eve have in the end?",
    "ground_truth": 226.8,
    "intermediate_values": [
      126.0,
      252.0,
      226.8
    ],
    "operations": [
      "multiply",
      "derived",
      "derived"
    ],
    "answer_unit": "$"
  },
  {
    "problem_id": "depth03_prob0162",
    "depth": 3,
    "question": "Bob gathers $12 per hour and works 7 hours. Bob spends $10 on boxes. Bob spends a quarter of Bob's remaining $ on apples. How much $ does Bob have in the end?",
    "ground_truth": 55.5,
    "intermediate_values": [
      84.0,
      74.0,
      55.5
    ],
    "operations": [
      "multiply",
      "derived",
      "derived"
    ],
    "answer_unit": "$"
  },
  {
    "problem_id": "depth03_prob0163",
    "depth": 3,
    "question": "Eve receives $6 per hour and works 4 hours. A 25% fee is deducted from Eve's total. Eve spends a quarter of Eve's remaining $ on books. How much $ does Eve have in the end?",
    "ground_truth": 13.5,
    "intermediate_values": [
      24.0,
      18.0,
      13.5
    ],
    "operations": [
      "multiply",
      "derived",
      "derived"
    ],
    "answer_unit": "$"
  },
  {
    "problem_id": "depth03_prob0164",
    "depth": 3,
    "question": "Bob collects $20 per hour and works 7 hours. Bob doubles Bob's current $ total. Bob spends half of Bob's remaining $ on boxes. How much $ does Bob have in the end?",
    "ground_truth": 140.0,
    "intermediate_values": [
      140.0,
      280.0,
      140.0
    ],
    "operations": [
      "multiply",
      "derived",
      "derived"
    ],
    "answer_unit": "$"
  },
  {
    "problem_id": "depth03_prob0165",
    "depth": 3,
    "question": "Alice earns $17 per hour and works 3 hours. Alice also receives a $9 bonus. Alice doubles Alice's current $ total. How much $ does Alice have in the end?",
    "ground_truth": 120.0,
    "intermediate_values": [
      51.0,
      60.0,
      120.0
    ],
    "operations": [
      "multiply",
      "derived",
      "derived"
    ],
    "answer_unit": "$"
  },
  {
    "problem_id": "depth03_prob0166",
    "depth": 3,
    "question": "Diana earns $8 per hour and works 5 hours. Diana also receives a $14 bonus. Diana spends a third of Diana's remaining $ on apples. How much $ does Diana have in the end?",
    "ground_truth": 36.0,
    "intermediate_values": [
      40.0,
      54.0,
      36.0
    ],
    "operations": [
      "multiply",
      "derived",
      "derived"
    ],
    "answer_unit": "$"
  },
  {
    "problem_id": "depth03_prob0167",
    "depth": 3,
    "question": "Carlos earns $13 per hour and works 9 hours. Carlos then picks up 5 apples at $5 each. A 25% fee is deducted from Carlos's total. How much $ does Carlos have in the end?",
    "ground_truth": 69.0,
    "intermediate_values": [
      117.0,
      92.0,
      69.0
    ],
    "operations": [
      "multiply",
      "derived",
      "derived"
    ],
    "answer_unit": "$"
  },
  {
    "problem_id": "depth03_prob0168",
    "depth": 3,
    "question": "Alice gathers $17 per hour and works 6 hours. Alice spends a third of Alice's remaining $ on books. Alice then buys 4 apples at $4 each. How much $ does Alice have in the end?",
    "ground_truth": 52.0,
    "intermediate_values": [
      102.0,
      68.0,
      52.0
    ],
    "operations": [
      "multiply",
      "derived",
      "derived"
    ],
    "answer_unit": "$"
  },
  {
    "problem_id": "depth03_prob0169",
    "depth": 3,
    "question": "Grace earns $20 per hour and works 6 hours. Grace spends a third of Grace's remaining $ on apples. A 10% fee is deducted from Grace's total. How much $ does Grace have in the end?",
    "ground_truth": 72.0,
    "intermediate_values": [
      120.0,
      80.0,
      72.0
    ],
    "operations": [
      "multiply",
      "derived",
      "derived"
    ],
    "answer_unit": "$"
  },
  {
    "problem_id": "depth03_prob0170",
    "depth": 3,
    "question": "Eve earns $13 per hour and works 4 hours. Eve also receives a $13 bonus. Eve spends half of Eve's remaining $ on books. How much $ does Eve have in the end?",
    "ground_truth": 32.5,
    "intermediate_values": [
      52.0,
      65.0,
      32.5
    ],
    "operations": [
      "multiply",
      "derived",
      "derived"
    ],
    "answer_unit": "$"
  },
  {
    "problem_id": "depth03_prob0171",
    "depth": 3,
    "question": "Bob receives $12 per hour and works 7 hours. A 10% fee is deducted from Bob's total. Bob spends half of Bob's remaining $ on boxes. How much $ does Bob have in the end?",
    "ground_truth": 37.8,
    "intermediate_values": [
      84.0,
      75.6,
      37.8
    ],
    "operations": [
      "multiply",
      "derived",
      "derived"
    ],
    "answer_unit": "$"
  },
  {
    "problem_id": "depth03_prob0172",
    "depth": 3,
    "question": "Diana earns $14 per hour and works 7 hours. Diana spends a quarter of Diana's remaining $ on boxes. Diana doubles Diana's current $ total. How much $ does Diana have in the end?",
    "ground_truth": 147.0,
    "intermediate_values": [
      98.0,
      73.5,
      147.0
    ],
    "operations": [
      "multiply",
      "derived",
      "derived"
    ],
    "answer_unit": "$"
  },
  {
    "problem_id": "depth03_prob0173",
    "depth": 3,
    "question": "Diana gathers $13 per hour and works 3 hours. Diana spends a third of Diana's remaining $ on boxes. Diana spends a quarter of Diana's remaining $ on books. How much $ does Diana have in the end?",
    "ground_truth": 19.5,
    "intermediate_values": [
      39.0,
      26.0,
      19.5
    ],
    "operations": [
      "multiply",
      "derived",
      "derived"
    ],
    "answer_unit": "$"
  },
  {
    "problem_id": "depth03_prob0174",
    "depth": 3,
    "question": "Henry gathers $10 per hour and works 3 hours. Henry spends a third of Henry's remaining $ on boxes. Henry gives away $4 on apples. How much $ does Henry have in the end?",
    "ground_truth": 16.0,
    "intermediate_values": [
      30.0,
      20.0,
      16.0
    ],
    "operations": [
      "multiply",
      "derived",
      "derived"
    ],
    "answer_unit": "$"
  },
  {
    "problem_id": "depth03_prob0175",
    "depth": 3,
    "question": "Eve earns $14 per hour and works 4 hours. Eve uses $5 on books. Eve spends a third of Eve's remaining $ on boxes. How much $ does Eve have in the end?",
    "ground_truth": 34.0,
    "intermediate_values": [
      56.0,
      51.0,
      34.0
    ],
    "operations": [
      "multiply",
      "derived",
      "derived"
    ],
    "answer_unit": "$"
  },
  {
    "problem_id": "depth03_prob0176",
    "depth": 3,
    "question": "Bob gathers $12 per hour and works 7 hours. Bob spends a quarter of Bob's remaining $ on apples. Bob spends a third of Bob's remaining $ on books. How much $ does Bob have in the end?",
    "ground_truth": 42.0,
    "intermediate_values": [
      84.0,
      63.0,
      42.0
    ],
    "operations": [
      "multiply",
      "derived",
      "derived"
    ],
    "answer_unit": "$"
  },
  {
    "problem_id": "depth03_prob0177",
    "depth": 3,
    "question": "Bob gathers $18 per hour and works 8 hours. Bob spends a quarter of Bob's remaining $ on apples. A 20% fee is deducted from Bob's total. How much $ does Bob have in the end?",
    "ground_truth": 86.4,
    "intermediate_values": [
      144.0,
      108.0,
      86.4
    ],
    "operations": [
      "multiply",
      "derived",
      "derived"
    ],
    "answer_unit": "$"
  },
  {
    "problem_id": "depth03_prob0178",
    "depth": 3,
    "question": "Eve earns $5 per hour and works 3 hours. Eve spends $3 on boxes. Eve spends a third of Eve's remaining $ on apples. How much $ does Eve have in the end?",
    "ground_truth": 8.0,
    "intermediate_values": [
      15.0,
      12.0,
      8.0
    ],
    "operations": [
      "multiply",
      "derived",
      "derived"
    ],
    "answer_unit": "$"
  },
  {
    "problem_id": "depth03_prob0179",
    "depth": 3,
    "question": "Frank receives $10 per hour and works 9 hours. Frank then purchases 3 books at $6 each. A 25% fee is deducted from Frank's total. How much $ does Frank have in the end?",
    "ground_truth": 54.0,
    "intermediate_values": [
      90.0,
      72.0,
      54.0
    ],
    "operations": [
      "multiply",
      "derived",
      "derived"
    ],
    "answer_unit": "$"
  },
  {
    "problem_id": "depth03_prob0180",
    "depth": 3,
    "question": "Eve earns $17 per hour and works 5 hours. Eve spends a quarter of Eve's remaining $ on boxes. Eve uses $3 on apples. How much $ does Eve have in the end?",
    "ground_truth": 60.75,
    "intermediate_values": [
      85.0,
      63.75,
      60.75
    ],
    "operations": [
      "multiply",
      "derived",
      "derived"
    ],
    "answer_unit": "$"
  },
  {
    "problem_id": "depth03_prob0181",
    "depth": 3,
    "question": "Frank earns $14 per hour and works 9 hours. Frank then purchases 2 boxes at $3 each. Frank spends half of Frank's remaining $ on books. How much $ does Frank have in the end?",
    "ground_truth": 60.0,
    "intermediate_values": [
      126.0,
      120.0,
      60.0
    ],
    "operations": [
      "multiply",
      "derived",
      "derived"
    ],
    "answer_unit": "$"
  },
  {
    "problem_id": "depth03_prob0182",
    "depth": 3,
    "question": "Bob collects $14 per hour and works 5 hours. Bob spends half of Bob's remaining $ on books. Bob doubles Bob's current $ total. How much $ does Bob have in the end?",
    "ground_truth": 70.0,
    "intermediate_values": [
      70.0,
      35.0,
      70.0
    ],
    "operations": [
      "multiply",
      "derived",
      "derived"
    ],
    "answer_unit": "$"
  },
  {
    "problem_id": "depth03_prob0183",
    "depth": 3,
    "question": "Diana collects $15 per hour and works 6 hours. A 20% fee is deducted from Diana's total. Diana donates $6 on books. How much $ does Diana have in the end?",
    "ground_truth": 66.0,
    "intermediate_values": [
      90.0,
      72.0,
      66.0
    ],
    "operations": [
      "multiply",
      "derived",
      "derived"
    ],
    "answer_unit": "$"
  },
  {
    "problem_id": "depth03_prob0184",
    "depth": 3,
    "question": "Grace receives $7 per hour and works 6 hours. Grace spends a quarter of Grace's remaining $ on apples. A 25% fee is deducted from Grace's total. How much $ does Grace have in the end?",
    "ground_truth": 23.625,
    "intermediate_values": [
      42.0,
      31.5,
      23.625
    ],
    "operations": [
      "multiply",
      "derived",
      "derived"
    ],
    "answer_unit": "$"
  },
  {
    "problem_id": "depth03_prob0185",
    "depth": 3,
    "question": "Diana gathers $20 per hour and works 4 hours. Diana then picks up 3 books at $2 each. A 20% fee is deducted from Diana's total. How much $ does Diana have in the end?",
    "ground_truth": 59.2,
    "intermediate_values": [
      80.0,
      74.0,
      59.2
    ],
    "operations": [
      "multiply",
      "derived",
      "derived"
    ],
    "answer_unit": "$"
  },
  {
    "problem_id": "depth03_prob0186",
    "depth": 3,
    "question": "Eve earns $8 per hour and works 3 hours. A 10% fee is deducted from Eve's total. Eve donates $6 on apples. How much $ does Eve have in the end?",
    "ground_truth": 15.6,
    "intermediate_values": [
      24.0,
      21.6,
      15.6
    ],
    "operations": [
      "multiply",
      "derived",
      "derived"
    ],
    "answer_unit": "$"
  },
  {
    "problem_id": "depth03_prob0187",
    "depth": 3,
    "question": "Henry collects $18 per hour and works 4 hours. Henry gives away $6 on boxes. Henry spends half of Henry's remaining $ on apples. How much $ does Henry have in the end?",
    "ground_truth": 33.0,
    "intermediate_values": [
      72.0,
      66.0,
      33.0
    ],
    "operations": [
      "multiply",
      "derived",
      "derived"
    ],
    "answer_unit": "$"
  },
  {
    "problem_id": "depth03_prob0188",
    "depth": 3,
    "question": "Henry earns $19 per hour and works 6 hours. Henry then orders 4 boxes at $2 each. Henry doubles Henry's current $ total. How much $ does Henry have in the end?",
    "ground_truth": 212.0,
    "intermediate_values": [
      114.0,
      106.0,
      212.0
    ],
    "operations": [
      "multiply",
      "derived",
      "derived"
    ],
    "answer_unit": "$"
  },
  {
    "problem_id": "depth03_prob0189",
    "depth": 3,
    "question": "Alice receives $14 per hour and works 5 hours. Alice spends a third of Alice's remaining $ on apples. Alice spends a quarter of Alice's remaining $ on boxes. How much $ does Alice have in the end?",
    "ground_truth": 35.0,
    "intermediate_values": [
      70.0,
      46.666666666666664,
      35.0
    ],
    "operations": [
      "multiply",
      "derived",
      "derived"
    ],
    "answer_unit": "$"
  },
  {
    "problem_id": "depth03_prob0190",
    "depth": 3,
    "question": "Eve earns $8 per hour and works 3 hours. Eve also receives a $11 bonus. Eve doubles Eve's current $ total. How much $ does Eve have in the end?",
    "ground_truth": 70.0,
    "intermediate_values": [
      24.0,
      35.0,
      70.0
    ],
    "operations": [
      "multiply",
      "derived",
      "derived"
    ],
    "answer_unit": "$"
  },
  {
    "problem_id": "depth03_prob0191",
    "depth": 3,
    "question": "Eve earns $17 per hour and works 3 hours. Eve spends a third of Eve's remaining $ on apples. Eve uses $7 on boxes. How much $ does Eve have in the end?",
    "ground_truth": 27.0,
    "intermediate_values": [
      51.0,
      34.0,
      27.0
    ],
    "operations": [
      "multiply",
      "derived",
      "derived"
    ],
    "answer_unit": "$"
  },
  {
    "problem_id": "depth03_prob0192",
    "depth": 3,
    "question": "Diana receives $15 per hour and works 9 hours. Diana spends half of Diana's remaining $ on apples. A 25% fee is deducted from Diana's total. How much $ does Diana have in the end?",
    "ground_truth": 50.625,
    "intermediate_values": [
      135.0,
      67.5,
      50.625
    ],
    "operations": [
      "multiply",
      "derived",
      "derived"
    ],
    "answer_unit": "$"
  },
  {
    "problem_id": "depth03_prob0193",
    "depth": 3,
    "question": "Carlos collects $19 per hour and works 10 hours. Carlos donates $10 on apples. Carlos spends a quarter of Carlos's remaining $ on boxes. How much $ does Carlos have in the end?",
    "ground_truth": 135.0,
    "intermediate_values": [
      190.0,
      180.0,
      135.0
    ],
    "operations": [
      "multiply",
      "derived",
      "derived"
    ],
    "answer_unit": "$"
  },
  {
    "problem_id": "depth03_prob0194",
    "depth": 3,
    "question": "Bob gathers $18 per hour and works 9 hours. Bob doubles Bob's current $ total. Bob spends a third of Bob's remaining $ on apples. How much $ does Bob have in the end?",
    "ground_truth": 216.0,
    "intermediate_values": [
      162.0,
      324.0,
      216.0
    ],
    "operations": [
      "multiply",
      "derived",
      "derived"
    ],
    "answer_unit": "$"
  },
  {
    "problem_id": "depth03_prob0195",
    "depth": 3,
    "question": "Diana collects $12 per hour and works 10 hours. Diana also receives a $15 bonus. Diana doubles Diana's current $ total. How much $ does Diana have in the end?",
    "ground_truth": 270.0,
    "intermediate_values": [
      120.0,
      135.0,
      270.0
    ],
    "operations": [
      "multiply",
      "derived",
      "derived"
    ],
    "answer_unit": "$"
  },
  {
    "problem_id": "depth03_prob0196",
    "depth": 3,
    "question": "Eve receives $18 per hour and works 9 hours. Eve then picks up 2 books at $4 each. Eve spends half of Eve's remaining $ on apples. How much $ does Eve have in the end?",
    "ground_truth": 77.0,
    "intermediate_values": [
      162.0,
      154.0,
      77.0
    ],
    "operations": [
      "multiply",
      "derived",
      "derived"
    ],
    "answer_unit": "$"
  },
  {
    "problem_id": "depth03_prob0197",
    "depth": 3,
    "question": "Carlos receives $17 per hour and works 7 hours. Carlos spends a third of Carlos's remaining $ on boxes. Carlos gives away $9 on apples. How much $ does Carlos have in the end?",
    "ground_truth": 70.33333333333333,
    "intermediate_values": [
      119.0,
      79.33333333333333,
      70.33333333333333
    ],
    "operations": [
      "multiply",
      "derived",
      "derived"
    ],
    "answer_unit": "$"
  },
  {
    "problem_id": "depth03_prob0198",
    "depth": 3,
    "question": "Grace gathers $10 per hour and works 4 hours. Grace also receives a $11 bonus. A 10% fee is deducted from Grace's total. How much $ does Grace have in the end?",
    "ground_truth": 45.9,
    "intermediate_values": [
      40.0,
      51.0,
      45.9
    ],
    "operations": [
      "multiply",
      "derived",
      "derived"
    ],
    "answer_unit": "$"
  },
  {
    "problem_id": "depth03_prob0199",
    "depth": 3,
    "question": "Bob collects $12 per hour and works 8 hours. Bob spends a quarter of Bob's remaining $ on books. Bob then buys 3 apples at $6 each. How much $ does Bob have in the end?",
    "ground_truth": 54.0,
    "intermediate_values": [
      96.0,
      72.0,
      54.0
    ],
    "operations": [
      "multiply",
      "derived",
      "derived"
    ],
    "answer_unit": "$"
  }
]